navmcp/__init__.py
navmcp/__main__.py
navmcp/app.py
navmcp/browser.py
navmcp/version.py
navmcp/tools/__init__.py
navmcp/tools/control.py
navmcp/tools/convert.py
navmcp/tools/fetch.py
navmcp/tools/interact.py
navmcp/tools/parse.py
navmcp/tools/pdf.py
navmcp/tools/save.py
navmcp/tools/search.py
navmcp/utils/__init__.py
navmcp/utils/io.py
navmcp/utils/net.py
navmcp/utils/parsing.py
navmcp-0.1.5.dist-info/licenses/LICENSE
navmcp-0.1.5.dist-info/METADATA
navmcp-0.1.5.dist-info/WHEEL
navmcp-0.1.5.dist-info/entry_points.txt
navmcp-0.1.5.dist-info/top_level.txt
navmcp-0.1.5.dist-info/RECORD
