Metadata-Version: 2.4
Name: navmcp
Version: 0.1.5
Summary: A browser automation server with FastAPI and MCP tools.
Author-email: jianlins <your@email.com>
License-Expression: MIT
Project-URL: Homepage, https://github.com/jianlins/navmcp
Requires-Python: >=3.8
License-File: LICENSE
Requires-Dist: fastapi
Requires-Dist: uvicorn
Requires-Dist: selenium
Requires-Dist: httpx
Requires-Dist: undetected-chromedriver
Requires-Dist: python-dotenv
Requires-Dist: loguru
Requires-Dist: chrome_version
Requires-Dist: pydantic
Requires-Dist: markitdown[docx,pdf]
Requires-Dist: markdownify
Requires-Dist: tenacity
Dynamic: license-file
